odoo/addons/report_qweb_encrypt/README.rst
odoo/addons/report_qweb_encrypt/__init__.py
odoo/addons/report_qweb_encrypt/__manifest__.py
odoo/addons/report_qweb_encrypt/controllers/__init__.py
odoo/addons/report_qweb_encrypt/controllers/main.py
odoo/addons/report_qweb_encrypt/i18n/report_qweb_encrypt.pot
odoo/addons/report_qweb_encrypt/models/__init__.py
odoo/addons/report_qweb_encrypt/models/ir_actions_report.py
odoo/addons/report_qweb_encrypt/readme/CONTRIBUTORS.rst
odoo/addons/report_qweb_encrypt/readme/DESCRIPTION.rst
odoo/addons/report_qweb_encrypt/readme/USAGE.rst
odoo/addons/report_qweb_encrypt/static/description/icon.png
odoo/addons/report_qweb_encrypt/static/description/index.html
odoo/addons/report_qweb_encrypt/static/src/js/report/action_manager_report.js
odoo/addons/report_qweb_encrypt/templates/assets.xml
odoo/addons/report_qweb_encrypt/tests/__init__.py
odoo/addons/report_qweb_encrypt/tests/test_report_qweb_encrypt.py
odoo/addons/report_qweb_encrypt/views/ir_actions_report.xml
odoo12_addon_report_qweb_encrypt-12.0.1.0.0.99.dev4.dist-info/METADATA
odoo12_addon_report_qweb_encrypt-12.0.1.0.0.99.dev4.dist-info/WHEEL
odoo12_addon_report_qweb_encrypt-12.0.1.0.0.99.dev4.dist-info/top_level.txt
odoo12_addon_report_qweb_encrypt-12.0.1.0.0.99.dev4.dist-info/RECORD
